appier_console/__init__.py
appier_console/base.py
appier_console/http.py
appier_console/util.py
appier_console/res/spinners.json
appier_console/test/__init__.py
appier_console/test/base.py
appier_console-0.3.1.dist-info/METADATA
appier_console-0.3.1.dist-info/WHEEL
appier_console-0.3.1.dist-info/top_level.txt
appier_console-0.3.1.dist-info/RECORD
